recode/__init__.py
recode/audio.py
recode/base.py
recode/util.py
recode-0.1.36.dist-info/LICENSE
recode-0.1.36.dist-info/METADATA
recode-0.1.36.dist-info/WHEEL
recode-0.1.36.dist-info/top_level.txt
recode-0.1.36.dist-info/RECORD
