Metadata-Version: 2.1
Name: recode
Version: 0.1.36
Summary: Tools to make codecs for time-series serialization and deserialization.
Home-page: https://github.com/i2mint/recode
Author: Thor Whalen
License: apache-2.0
Keywords: time-series,serialization,deserialization,codec,audio
Platform: any
License-File: LICENSE
